autoglm_webui_lib/__init__.py
autoglm_webui_lib/config_manager.py
autoglm_webui_lib/device_manager.py
autoglm_webui_lib/local_server.py
autoglm_webui_lib/remote_server.py
autoglm_webui_lib/start_local.py
autoglm_webui_lib/start_remote.py
autoglm_webui_lib/task_runner.py
autoglm_webui_lib/phone_agent/__init__.py
autoglm_webui_lib/phone_agent/agent.py
autoglm_webui_lib/phone_agent/agent_ios.py
autoglm_webui_lib/phone_agent/device_factory.py
autoglm_webui_lib/phone_agent/__pycache__/__init__.cpython-312.pyc
autoglm_webui_lib/phone_agent/__pycache__/agent.cpython-312.pyc
autoglm_webui_lib/phone_agent/__pycache__/agent_ios.cpython-312.pyc
autoglm_webui_lib/phone_agent/__pycache__/device_factory.cpython-312.pyc
autoglm_webui_lib/phone_agent/actions/__init__.py
autoglm_webui_lib/phone_agent/actions/handler.py
autoglm_webui_lib/phone_agent/actions/handler_ios.py
autoglm_webui_lib/phone_agent/actions/__pycache__/__init__.cpython-312.pyc
autoglm_webui_lib/phone_agent/actions/__pycache__/handler.cpython-312.pyc
autoglm_webui_lib/phone_agent/actions/__pycache__/handler_ios.cpython-312.pyc
autoglm_webui_lib/phone_agent/adb/__init__.py
autoglm_webui_lib/phone_agent/adb/connection.py
autoglm_webui_lib/phone_agent/adb/device.py
autoglm_webui_lib/phone_agent/adb/input.py
autoglm_webui_lib/phone_agent/adb/screenshot.py
autoglm_webui_lib/phone_agent/config/__init__.py
autoglm_webui_lib/phone_agent/config/apps.py
autoglm_webui_lib/phone_agent/config/apps_harmonyos.py
autoglm_webui_lib/phone_agent/config/apps_ios.py
autoglm_webui_lib/phone_agent/config/i18n.py
autoglm_webui_lib/phone_agent/config/prompts.py
autoglm_webui_lib/phone_agent/config/prompts_en.py
autoglm_webui_lib/phone_agent/config/prompts_zh.py
autoglm_webui_lib/phone_agent/config/timing.py
autoglm_webui_lib/phone_agent/hdc/__init__.py
autoglm_webui_lib/phone_agent/hdc/connection.py
autoglm_webui_lib/phone_agent/hdc/device.py
autoglm_webui_lib/phone_agent/hdc/input.py
autoglm_webui_lib/phone_agent/hdc/screenshot.py
autoglm_local-1.4.1.dist-info/METADATA
autoglm_local-1.4.1.dist-info/WHEEL
autoglm_local-1.4.1.dist-info/entry_points.txt
autoglm_local-1.4.1.dist-info/top_level.txt
autoglm_local-1.4.1.dist-info/RECORD
