Metadata-Version: 2.1
Name: autoglm-local
Version: 1.4.1
Summary: AutoGLM AI-APPUI 自动化测试平台 - 本地客户端（内置完整依赖）
Home-page: http://qa.local:8787/zsdx/AI_UIauto_app
Author: chenwenkun
Author-email: 
Keywords: appium,automation,testing,android,ios,ai
Classifier: Programming Language :: Python :: 3
Classifier: Programming Language :: Python :: 3.8
Classifier: Programming Language :: Python :: 3.9
Classifier: Programming Language :: Python :: 3.10
Classifier: Programming Language :: Python :: 3.11
Classifier: Programming Language :: Python :: 3.12
Classifier: License :: OSI Approved :: MIT License
Classifier: Operating System :: OS Independent
Classifier: Topic :: Software Development :: Testing
Classifier: Topic :: Software Development :: Quality Assurance
Requires-Python: >=3.8
Requires-Dist: fastapi >=0.100.0
Requires-Dist: uvicorn >=0.22.0
Requires-Dist: websockets >=11.0
Requires-Dist: python-multipart >=0.0.6
Requires-Dist: httpx >=0.24.0
Requires-Dist: openai >=1.0.0
Requires-Dist: adbutils >=2.0.0
Requires-Dist: tidevice >=0.12.0
Requires-Dist: loguru >=0.7.0
Requires-Dist: requests >=2.28.0
Requires-Dist: pydantic >=2.0.0
Requires-Dist: Pillow >=10.0.0
Requires-Dist: openpyxl >=3.1.0
